xcmd/__init__.py
xcmd/complete.py
xcmd/conf.py
xcmd/conf_store.py
xcmd/util.py
xcmd/xcmd.py
xcmd/tests/__init__.py
xcmd/tests/test_complete.py
xcmd/tests/test_conf.py
xcmd/tests/test_conf_store.py
xcmd/tests/test_params_parsing.py
xcmd/tests/test_util.py
xcmd/tests/test_xcmd.py
xcmd-0.0.4.data/scripts/xcmd-shell
xcmd-0.0.4.dist-info/LICENSE
xcmd-0.0.4.dist-info/METADATA
xcmd-0.0.4.dist-info/WHEEL
xcmd-0.0.4.dist-info/top_level.txt
xcmd-0.0.4.dist-info/RECORD
