Metadata-Version: 2.1
Name: xcmd
Version: 0.0.4
Summary: UNKNOWN
Home-page: UNKNOWN
Author: rgs
Author-email: rgs@itevenworks.net
License: apache
Platform: UNKNOWN
Classifier: Development Status :: 3 - Alpha
Classifier: License :: OSI Approved :: Apache Software License
Classifier: Programming Language :: Python
Classifier: Programming Language :: Python :: 2.7
Classifier: Programming Language :: Python :: 3
Provides-Extra: test
